[
    {
        "id": "BOT-001",
        "name": "Autenticador Automático",
        "performance": [
            {
                "title": "Autenticaciones por minuto",
                "time": 5000,
                "rate": 92
            },
            {
                "title": "Tokens generados",
                "time": 10000,
                "rate": 95
            },
            {
                "title": "Intentos fallidos",
                "time": 15000,
                "rate": 5
            },
            {
                "title": "Sesiones activas",
                "time": 20000,
                "rate": 87
            }
        ],
        "description": "Sistema de autenticación seguro que gestiona logins y recuperación de contraseñas mediante tokens JWT",
        "createdAt": "20/02/2025",
        "lastUpdate": "20/08/2025",
        "type": "security",
        "status": "active",
        "completeRate": 92,
        "intervalTime": 5000,
        "processes": {
            "name": "Login de usuarios",
            "steps": [
                "Captura credenciales",
                "Valida en base de datos",
                "Genera token JWT",
                "Establece sesión"
            ],
            "automatedActions": [
                "Autenticación en segundo plano",
                "Generación automática de tokens",
                "Expiración y renovación de sesiones",
                "Notificación de intentos fallidos"
            ],
            "integrations": [
                "Okta (SSO)",
                "Active Directory",
                "Auth0",
                "Duo Security (MFA)",
                "Ping Identity",
                "AWS Cognito"
            ],
            "frequency": "Por solicitud",
            "dataTypes": [
                "credenciales",
                "tokens",
                "logs de acceso"
            ],
            "workflow": [
                "Usuario ingresa credenciales",
                "Validación contra base de datos",
                "Generación de token JWT",
                "Creación de sesión segura",
                "Envío de respuesta al cliente"
            ]
        }
    },
    {
        "id": "BOT-002",
        "name": "Generador de Contenido",
        "performance": [
            {
                "title": "Publicaciones generadas",
                "time": 6000,
                "rate": 85
            },
            {
                "title": "Correcciones realizadas",
                "time": 4000,
                "rate": 10
            },
            {
                "title": "Publicaciones programadas",
                "time": 7000,
                "rate": 75
            },
            {
                "title": "Optimización SEO",
                "time": 5000,
                "rate": 90
            }
        ],
        "description": "Bot de marketing que crea y programa contenido optimizado para SEO en redes sociales y blogs",
        "createdAt": "15/01/2025",
        "lastUpdate": "10/09/2025",
        "type": "marketing",
        "status": "active",
        "completeRate": 85,
        "intervalTime": 8000,
        "processes": {
            "name": "Creación de posts",
            "steps": [
                "Recibe tema principal",
                "Genera borrador",
                "Revisión de calidad",
                "Publicación automática"
            ],
            "automatedActions": [
                "Generación automática de posts",
                "Optimización SEO en tiempo real",
                "Publicación programada en redes",
                "Análisis de engagement"
            ],
            "integrations": [
                "HubSpot (Marketing)",
                "Hootsuite (Redes Sociales)",
                "WordPress (CMS)",
                "Google Analytics",
                "SEMrush (SEO)",
                "Mailchimp (Email Marketing)"
            ],
            "frequency": "Cada 6 horas",
            "dataTypes": [
                "texto",
                "metadata SEO",
                "métricas de engagement",
                "keywords"
            ],
            "workflow": [
                "Recepción de tema principal",
                "Generación de contenido base",
                "Optimización SEO",
                "Revisión de calidad",
                "Programación de publicación",
                "Distribución en canales"
            ]
        }
    },
    {
        "id": "BOT-003",
        "name": "Asistente de Soporte",
        "performance": [
            {
                "title": "Tickets atendidos",
                "time": 2500,
                "rate": 78
            },
            {
                "title": "Respuestas automáticas",
                "time": 3000,
                "rate": 80
            },
            {
                "title": "Tiempo promedio",
                "time": 2000,
                "rate": 85
            },
            {
                "title": "Resoluciones efectivas",
                "time": 3500,
                "rate": 88
            }
        ],
        "description": "Sistema de tickets inteligente que clasifica y deriva consultas según prioridad y especialidad requerida",
        "createdAt": "03/03/2025",
        "lastUpdate": "25/07/2025",
        "type": "helpdesk",
        "status": "active",
        "completeRate": 78,
        "intervalTime": 3000,
        "processes": {
            "name": "Gestión de tickets",
            "steps": [
                "Clasifica consulta",
                "Asigna prioridad",
                "Deriva a especialista",
                "Seguimiento automático"
            ],
            "automatedActions": [
                "Clasificación automática de tickets",
                "Asignación de prioridades",
                "Derivación a especialistas",
                "Seguimiento y cierre de casos"
            ],
            "integrations": [
                "Zendesk (Ticketing)",
                "Slack (Notificaciones)",
                "Jira Service Desk",
                "Freshdesk",
                "Intercom (Chat)",
                "WhatsApp Business API"
            ],
            "frequency": "Tiempo real",
            "dataTypes": [
                "texto",
                "categorías",
                "prioridades",
                "tiempos de respuesta"
            ],
            "workflow": [
                "Recepción de ticket",
                "Análisis de contenido",
                "Clasificación automática",
                "Asignación de prioridad",
                "Derivación a área correspondiente",
                "Seguimiento hasta resolución"
            ]
        }
    },
    {
        "id": "BOT-004",
        "name": "Monitor de Sistemas",
        "performance": [
            {
                "title": "Servidores monitoreados",
                "time": 1000,
                "rate": 95
            },
            {
                "title": "Incidentes detectados",
                "time": 5000,
                "rate": 12
            },
            {
                "title": "Auto-remediaciones ejecutadas",
                "time": 2000,
                "rate": 85
            },
            {
                "title": "Alertas enviadas",
                "time": 3000,
                "rate": 90
            }
        ],
        "description": "Monitorización 24/7 de servidores con capacidad de auto-remediación para incidentes comunes",
        "createdAt": "12/12/2024",
        "lastUpdate": "01/09/2025",
        "type": "devops",
        "status": "active",
        "completeRate": 95,
        "intervalTime": 2000,
        "processes": {
            "name": "Chequeo de servidores",
            "steps": [
                "Escaneo de recursos",
                "Detección anomalías",
                "Notificación alertas",
                "Auto-remediación"
            ],
            "automatedActions": [
                "Detección de fallos en servidores",
                "Auto-remediación de errores",
                "Envío de alertas en tiempo real",
                "Generación de reportes de estado"
            ],
            "integrations": [
                "Datadog (Monitoring)",
                "PagerDuty (Alerting)",
                "New Relic (APM)",
                "Prometheus (Metrics)",
                "Grafana (Dashboards)",
                "Splunk (Logs)"
            ],
            "frequency": "Cada 5 minutos",
            "dataTypes": [
                "métricas",
                "logs",
                "alertas",
                "estado de servicios"
            ],
            "workflow": [
                "Escaneo programado de recursos",
                "Comparación con umbrales",
                "Detección de desviaciones",
                "Ejecución de remediaciones predefinidas",
                "Notificación a equipos si es necesario",
                "Generación de reporte"
            ]
        }
    },
    {
        "id": "BOT-005",
        "name": "Analizador de Datos",
        "performance": [
            {
                "title": "Datos procesados",
                "time": 8000,
                "rate": 88
            },
            {
                "title": "Anomalías detectadas",
                "time": 9000,
                "rate": 10
            },
            {
                "title": "Reportes generados",
                "time": 7000,
                "rate": 90
            },
            {
                "title": "Distribución de insights",
                "time": 10000,
                "rate": 85
            }
        ],
        "description": "Plataforma analítica que genera reportes ejecutivos y detecta anomalías en datasets corporativos",
        "createdAt": "22/05/2025",
        "lastUpdate": "18/08/2025",
        "type": "analytics",
        "status": "active",
        "completeRate": 88,
        "intervalTime": 10000,
        "processes": {
            "name": "Reportes diarios",
            "steps": [
                "Extracción datos",
                "Procesamiento ETL",
                "Generación visualizaciones",
                "Distribución automática"
            ],
            "automatedActions": [
                "Extracción y limpieza de datos",
                "Generación de visualizaciones",
                "Detección de anomalías",
                "Distribución automática de reportes"
            ],
            "integrations": [
                "Tableau (Visualización)",
                "Power BI",
                "Snowflake (Data Warehouse)",
                "Google BigQuery",
                "Looker",
                "Apache Superset"
            ],
            "frequency": "Diario",
            "dataTypes": [
                "datasets",
                "métricas KPI",
                "tendencias",
                "anomalías"
            ],
            "workflow": [
                "Extracción de fuentes de datos",
                "Transformación y limpieza",
                "Cálculo de métricas clave",
                "Generación de visualizaciones",
                "Revisión de calidad",
                "Distribución a destinatarios"
            ]
        }
    }
]